brain_games/.DS_Store
brain_games/__init__.py
brain_games/cli.py
brain_games/games/calc.py
brain_games/games/gcd.py
brain_games/games/is_even.py
brain_games/games/is_prime.py
brain_games/games/progression.py
brain_games/play_game.py
brain_games/scripts/.DS_Store
brain_games/scripts/__init__.py
brain_games/scripts/brain_calc.py
brain_games/scripts/brain_even.py
brain_games/scripts/brain_games.py
brain_games/scripts/brain_gcd.py
brain_games/scripts/brain_prime.py
brain_games/scripts/brain_progression.py
mo_brain_games-0.7.0.dist-info/entry_points.txt
mo_brain_games-0.7.0.dist-info/WHEEL
mo_brain_games-0.7.0.dist-info/METADATA
mo_brain_games-0.7.0.dist-info/RECORD
