Metadata-Version: 2.1
Name: mo-brain-games
Version: 0.7.0
Summary: 
Author: Max Odinokiy
Author-email: max.odinokiy@gmail.com
Requires-Python: >=3.10,<4.0
Classifier: Programming Language :: Python :: 3
Classifier: Programming Language :: Python :: 3.10
Requires-Dist: prompt (>=0.4.1,<0.5.0)
